lmc_runner
