Metadata-Version: 2.1
Name: lmc-runner
Version: 0.0.2
Summary: Run LMC assembly code!
Home-page: https://github.com/dhruvnps/lmc-runner
Author: dhruvnps
License: UNKNOWN
Platform: UNKNOWN
Classifier: Programming Language :: Python :: 3
Classifier: License :: OSI Approved :: Apache Software License
Classifier: Operating System :: OS Independent
Requires-Python: >=3.6
